{"version": 0.6, "generator": "Overpass API 0.7.62.8 e802775f", "osm3s": {"timestamp_osm_base": "2025-09-13T15:01:51Z", "copyright": "The data included in this document is from www.openstreetmap.org. The data is made available under ODbL."}, "elements": [{"type": "node", "id": 5401398493, "lat": 28.4239334, "lon": 77.3421965}, {"type": "node", "id": 5401398494, "lat": 28.4239203, "lon": 77.343201}, {"type": "node", "id": 5401398495, "lat": 28.4235291, "lon": 77.343216}, {"type": "node", "id": 5401398496, "lat": 28.4234983, "lon": 77.3429861}, {"type": "node", "id": 5401398497, "lat": 28.4232654, "lon": 77.3429761}, {"type": "node", "id": 5401398498, "lat": 28.4233269, "lon": 77.3421815}, {"type": "node", "id": 5401506215, "lat": 28.4233234, "lon": 77.3422266}, {"type": "way", "id": 560102821, "nodes": [5401398493, 5401398494, 5401398495, 5401398496, 5401398497, 5401506215, 5401398498, 5401398493], "tags": {"landuse": "farmyard"}}]}